latent_ideology/__init__.py
latent_ideology/latent_ideology_class.py
latent_ideology-0.0.5.dist-info/LICENSE.txt
latent_ideology-0.0.5.dist-info/METADATA
latent_ideology-0.0.5.dist-info/WHEEL
latent_ideology-0.0.5.dist-info/top_level.txt
latent_ideology-0.0.5.dist-info/RECORD
