Metadata-Version: 2.1
Name: latent-ideology
Version: 0.0.5
Summary: Latent ideology method
Home-page: https://github.com/fedemoss
Download-URL: https://github.com/fedemoss/-source-code-latent-method/archive/refs/tags/0.0.5.tar.gz
Author: Fede Moss
Author-email: fedemoss@gmail.com
License: MIT
Project-URL: Bug Tracker, https://https://github.com/fedemoss/latent_ideology
Keywords: correspondence analysis,latent ideology
Classifier: Development Status :: 3 - Alpha
Classifier: Intended Audience :: Developers
Classifier: Topic :: Software Development :: Documentation
Classifier: License :: OSI Approved :: MIT License
Classifier: Programming Language :: Python :: 3
Classifier: Programming Language :: Python :: 3.7
Classifier: Programming Language :: Python :: 3.8
Classifier: Programming Language :: Python :: 3.9
License-File: LICENSE.txt
Requires-Dist: pandas
Requires-Dist: numpy
Requires-Dist: scipy
